fastapi_auth_toolkit/__init__.py
fastapi_auth_toolkit/app/__init__.py
fastapi_auth_toolkit/app/config.py
fastapi_auth_toolkit/app/events.py
fastapi_auth_toolkit/app/middlewares.py
fastapi_auth_toolkit/app/events/profile.py
fastapi_auth_toolkit/app/exception/__init__.py
fastapi_auth_toolkit/app/exception/database.py
fastapi_auth_toolkit/app/exception/permissions.py
fastapi_auth_toolkit/app/exception/response.py
fastapi_auth_toolkit/app/exception/token.py
fastapi_auth_toolkit/app/helpers/__init__.py
fastapi_auth_toolkit/app/helpers/operations.py
fastapi_auth_toolkit/app/models/mixin/base.py
fastapi_auth_toolkit/app/models/mixin/date_and_time.py
fastapi_auth_toolkit/app/permissions/__init__.py
fastapi_auth_toolkit/app/schemas/database.py
fastapi_auth_toolkit/app/schemas/jwt.py
fastapi_auth_toolkit/app/services/jwt.py
fastapi_auth_toolkit/app/services/password.py
fastapi_auth_toolkit/app/settings/__init__.py
fastapi_auth_toolkit/app/settings/cookies.py
fastapi_auth_toolkit/app/settings/jwt.py
fastapi_auth_toolkit/app/settings/session.py
fastapi_auth_toolkit/app/utils/__init__.py
fastapi_auth_toolkit/app/utils/decorators.py
fastapi_auth_toolkit/app/utils/functions.py
fastapi_auth_toolkit/app/utils/enums/__init__.py
fastapi_auth_toolkit/app/utils/enums/auth.py
fastapi_auth_toolkit/app/utils/enums/base.py
fastapi_auth_toolkit/app/utils/enums/database.py
fastapi_auth_toolkit/app/utils/enums/response.py
fastapi_auth_toolkit/app/views/__init__.py
fastapi_auth_toolkit/app/views/base.py
fastapi_auth_toolkit/auth/__init__.py
fastapi_auth_toolkit/auth/middlewares.py
fastapi_auth_toolkit/auth/routers.py
fastapi_auth_toolkit/auth/api/__init__.py
fastapi_auth_toolkit/auth/api/auth.py
fastapi_auth_toolkit/auth/api/roles.py
fastapi_auth_toolkit/auth/api/user.py
fastapi_auth_toolkit/auth/config/authentication.py
fastapi_auth_toolkit/auth/events/profile.py
fastapi_auth_toolkit/auth/exception/__init__.py
fastapi_auth_toolkit/auth/exception/authentication.py
fastapi_auth_toolkit-0.0.2.dist-info/LICENSE
fastapi_auth_toolkit-0.0.2.dist-info/METADATA
fastapi_auth_toolkit-0.0.2.dist-info/WHEEL
fastapi_auth_toolkit-0.0.2.dist-info/top_level.txt
fastapi_auth_toolkit-0.0.2.dist-info/RECORD
